Metadata-Version: 1.1
Name: hci-protocol
Version: 0.0.4
Summary: HCI Packet Parser
Home-page: https://github.com/Jumperr-labs/hci-protocol
Author: Jumper Team
Author-email: info@jumper.io
License: Apache 2.0
Download-URL: https://github.com/Jumperr-labs/hci-protocol/archive/0.0.4.tar.gz
Keywords: ble,bluetooth,hci,parsing,jumper
Platform: UNKNOWN
Classifier: Development Status :: 3 - Alpha
Classifier: Intended Audience :: Developers
Classifier: Topic :: Software Development :: Embedded Systems
Classifier: Programming Language :: Python :: 2
Classifier: Programming Language :: Python :: 2.7
Classifier: Programming Language :: Python :: 3
Classifier: Programming Language :: Python :: 3.3
Classifier: Programming Language :: Python :: 3.4
Classifier: Programming Language :: Python :: 3.5
